{
  "abilities": [
    {
      "id": "vein_miner",
      "name": "Vein Miner",
      "description": "Mine entire veins of ore at once",
      "requiredLevel": 10,
      "cooldown": 60,
      "activation": {
        "type": "BLOCK_BREAK",
        "blocks": ["IRON_ORE", "GOLD_ORE", "DIAMOND_ORE"],
        "toolTypes": ["PICKAXE"]
      }
    },
    {
      "id": "tree_feller",
      "name": "Tree Feller",
      "description": "Cut down entire trees at once",
      "requiredLevel": 15,
      "cooldown": 120,
      "activation": {
        "type": "BLOCK_BREAK",
        "blocks": ["OAK_LOG", "BIRCH_LOG"],
        "toolTypes": ["AXE"]
      }
    }
  ]
}
